azureml/__init__.py
azureml/contrib/__init__.py
azureml/contrib/pipeline/__init__.py
azureml/contrib/pipeline/steps/__init__.py
azureml/contrib/pipeline/steps/parallel_run_config.py
azureml/contrib/pipeline/steps/parallel_run_step.py
azureml_contrib_pipeline_steps-1.60.0.dist-info/licenses/LICENSE.txt
azureml_contrib_pipeline_steps-1.60.0.dist-info/METADATA
azureml_contrib_pipeline_steps-1.60.0.dist-info/WHEEL
azureml_contrib_pipeline_steps-1.60.0.dist-info/top_level.txt
azureml_contrib_pipeline_steps-1.60.0.dist-info/RECORD
