Metadata-Version: 2.4
Name: azureml-contrib-pipeline-steps
Version: 1.60.0
Summary: Azure Machine Learning Parallel Run Step - Deprecated
Home-page: https://docs.microsoft.com/python/api/overview/azure/ml/?view=azure-ml-py
Author: Microsoft Corp
License: Proprietary https://aka.ms/azureml-preview-sdk-license 
Requires-Python: >=3.7,<4.0
License-File: LICENSE.txt
Requires-Dist: azureml-core~=1.60.0
Requires-Dist: azureml-dataset-runtime~=1.60.0
Requires-Dist: azureml-pipeline-core~=1.60.0
Dynamic: author
Dynamic: description
Dynamic: description-content-type
Dynamic: home-page
Dynamic: license
Dynamic: license-file
Dynamic: requires-dist
Dynamic: requires-python
Dynamic: summary
